agent_a2z_payment/__init__.py
agent_a2z_payment/constants.py
agent_a2z_payment/core.py
agent_a2z_payment/web/checkout/checkout_failure.html
agent_a2z_payment/web/checkout/checkout_scripts.js
agent_a2z_payment/web/checkout/checkout_success.html
agent_a2z_payment/web/checkout/checkout_template.html
agent_a2z_payment-0.0.6.dist-info/METADATA
agent_a2z_payment-0.0.6.dist-info/WHEEL
agent_a2z_payment-0.0.6.dist-info/top_level.txt
agent_a2z_payment-0.0.6.dist-info/RECORD
