Metadata-Version: 2.4
Name: agent_a2z_payment
Version: 0.0.6
Summary: Agent Payment and Billing SDK Integration, Supports All Popular Payment methods Stripe,Paypal,Alipay,WeChat,A2ZAgent Credit Payment. Billing Agent to add transaction and do analysis on expenditure
Author-email: aihubadmin@126.com
License: MIT License
Project-URL: Homepage, https://www.deepnlp.org/store/ai-agent
Project-URL: Repository, https://github.com/aiagenta2z/agent_a2z_payment
Keywords: Payment Agent,In Agent Purchase,Stripe,Paypal,Alipay,WeChat
Classifier: Development Status :: 3 - Alpha
Classifier: Intended Audience :: Developers
Classifier: Topic :: Software Development :: Build Tools
Classifier: License :: OSI Approved :: MIT License
Requires-Python: >=3.9
Requires-Dist: requests>=2.17.0
Requires-Dist: tiktoken>=0.5.0
Requires-Dist: stripe>=5.0.0
